{"bing_fil": ["9", "5", "3", "X", "X", "7", "4", "8", "X", "X"], "google": ["X", "X", "3", "X", "X", "7", "X", "8", "X", "X"], "sphinx": ["none", "bye", "hurry", "the", "god", "heaven", "oh", "a guy", "they", "good"], "ibm": ["X", "X", "three", "X", "one", "that", "or", "a", "it", "they"], "google_fil": ["X", "X", "3", "X", "X", "7", "X", "8", "X", "X"], "wit": ["nine", "five", "three", "", "one", "seven", "what are", "eight", "", ""], "bing": ["nine", "five", "three", "thanks", "launch", "seven", "four", "eight", "X", "it"], "sphinx_fil": ["X", "X", "X", "X", "X", "X", "X", "X", "X", "X"], "googleCloud_fil": ["9", "X", "3", "X", "X", "7", "4", "8", "X", "8"], "wit_fil": ["9", "5", "3", "X", "1", "7", "X", "8", "X", "X"], "ibm_fil": ["X", "X", "3", "X", "1", "X", "X", "X", "X", "X"], "final": "XX3XX7X8XX", "googleCloud": ["nine", "X", "three", "X", "X", "seven", "four", "eight", "X", "eight"]}