{"bing_fil": ["99", "55", "33", "666", null, "77", "44", "888", null, "68"], "google": ["X", "X", "3", "X", "X", "7", "X", "8", "X", "X"], "sphinx": ["none", "bye", "hurry", "the", "god", "heaven", "oh", "a guy", "they", "good"], "ibm": ["X", "X", "three", "X", "one", "that", "or", "a", "it", "they"], "google_fil": [null, null, "33", null, null, "77", null, "888", null, null], "wit": ["nine", "five", "three", "", "one", "seven", "what are", "eight", "", ""], "bing": ["nine", "five", "three", "thanks", "launch", "seven", "four", "eight", "X", "it"], "sphinx_fil": ["9", "59", "3", null, null, "7", null, null, "8", null], "googleCloud_fil": ["99", null, "33", null, null, "77", "44", "888", null, "888"], "wit_fil": ["99", "55", "33", null, "11", "77", null, "888", null, null], "ibm_fil": [null, null, "33", null, "11", null, "44", "8", "68", "8"], "final": "9536174888", "googleCloud": ["nine", "X", "three", "X", "X", "seven", "four", "eight", "X", "eight"]}