{"google": ["X", "X", "X", "X", "X", "X", "X", "X", "3", "8"], "sphinx_fil": ["0", "X", "X", "1", "X", "X", "4", "X", "8", "X"], "wit": ["well", "four", "", "seven", "five", "five", "four", "", "three", "hey"], "time3": 2.567842960357666, "time8": 3.0220530033111572, "time9": 2.6674118041992188, "time4": 4.056627035140991, "time5": 1.6648049354553223, "time6": 2.384913921356201, "time7": 2.6507999897003174, "time0": 2.2443041801452637, "time1": 1.8640961647033691, "time2": 2.2976021766662598, "googleCloud_fil": ["0", "X", "X", "7", "X", "5", "4", "X", "3", "8"], "final": "0407554938", "total_time": 25.642723083496094, "bing_fil": ["0", "4", "X", "7", "5", "5", "4", "9", "3", "X"], "houndify": ["X", "X", "X", "X", "X", "X", "X", "X", "X", "X"], "wit_fil": ["X", "4", "X", "7", "5", "5", "4", "X", "3", "8"], "googleCloud": ["zero", "X", "X", "seven", "X", "five", "four", "X", "three", "eight"], "sphinx": ["the hero", "they are", "he had", "done", "why", "bye", "four", "good", "they", "they had"], "ibm": ["yeah", "for", "yeah", "there", "by", "by", "for", "not", "very", "they"], "google_fil": ["X", "X", "X", "X", "X", "X", "X", "X", "3", "8"], "bing": ["zero", "four", "X", "seven", "five", "five", "four", "no", "three", "face"], "ibm_fil": ["0", "4", "0", "X", "X", "X", "4", "X", "3", "8"], "houndify_fil": ["X", "X", "X", "X", "X", "X", "X", "X", "X", "X"]}